Metadata-Version: 2.1
Name: model-card
Version: 0.1.3
Summary: Model Card Toolkit
Home-page: https://github.com/model-card/model-card
Author: Adrin Jalali
Author-email: adrin.jalali@gmail.com
License: Apache 2.0
Keywords: model card toolkit ml metadata machine learning
Platform: UNKNOWN
Classifier: Development Status :: 4 - Beta
Classifier: Intended Audience :: Developers
Classifier: Intended Audience :: Education
Classifier: Intended Audience :: Science/Research
Classifier: License :: OSI Approved :: Apache Software License
Classifier: Operating System :: OS Independent
Classifier: Programming Language :: Python :: 3
Classifier: Programming Language :: Python :: 3.7
Classifier: Programming Language :: Python :: 3 :: Only
Classifier: Topic :: Scientific/Engineering
Classifier: Topic :: Scientific/Engineering :: Mathematics
Classifier: Topic :: Scientific/Engineering :: Artificial Intelligence
Classifier: Topic :: Software Development
Classifier: Topic :: Software Development :: Libraries
Classifier: Topic :: Software Development :: Libraries :: Python Modules
Requires-Python: >=3.6,<4
Requires-Dist: absl-py (<0.11,>=0.9)
Requires-Dist: semantic-version (<3,>=2.8.0)
Requires-Dist: jinja2 (<3,>=2.10)
Requires-Dist: matplotlib (<4,>=3.2.0)
Requires-Dist: jsonschema (<4,>=3.2.0)
Requires-Dist: tensorflow-data-validation (<0.27.0,>=0.26.0)
Requires-Dist: tensorflow-model-analysis (<0.27.0,>=0.26.0)
Requires-Dist: tensorflow-metadata (<0.27.0,>=0.26.0)
Requires-Dist: ml-metadata (<0.27.0,>=0.26.0)
Requires-Dist: dataclasses ; python_version < "3.7"
